nlu_trainer/__init__.py
nlu_trainer/_config.py
nlu_trainer/cli.py
nlu_trainer/configs/corpus.yaml
nlu_trainer/configs/dataset.yaml
nlu_trainer/configs/docs.yaml
nlu_trainer/configs/domain.yaml
nlu_trainer/configs/intention.yaml
nlu_trainer/configs/ner.yaml
nlu_trainer/corpus/Generator.jar
nlu_trainer/corpus/abnf/.DS_Store
nlu_trainer/corpus/abnf/run.sh
nlu_trainer/corpus/neg_extra.txt
nlu_trainer/corpus/pos_extra.txt
nlu_trainer/layers.py
nlu_trainer/metrics.py
nlu_trainer/model.py
nlu_trainer/prepare.py
nlu_trainer/push.exp
nlu_trainer/push.py
nlu_trainer/scheduler.py
nlu_trainer/test.py
nlu_trainer/train.py
nlu_trainer/utils.py
nlu_trainer-0.2.1.dist-info/METADATA
nlu_trainer-0.2.1.dist-info/WHEEL
nlu_trainer-0.2.1.dist-info/entry_points.txt
nlu_trainer-0.2.1.dist-info/RECORD
