Metadata-Version: 2.1
Name: nlu-trainer
Version: 0.2.1
Summary: 普强信息语言理解模型训练框架
Author: wangmengdi
Author-email: wangmengdi@pachiratech.com
Requires-Python: >=3.7
Classifier: Programming Language :: Python :: 3
Classifier: Programming Language :: Python :: 3.7
Classifier: Programming Language :: Python :: 3.8
Classifier: Programming Language :: Python :: 3.9
Classifier: Programming Language :: Python :: 3.10
Classifier: Programming Language :: Python :: 3.11
Requires-Dist: datasets (>=2.14.5)
Requires-Dist: fasttext (>=0.9.1)
Requires-Dist: jsonargparse[signatures] (>=4.26.0)
Requires-Dist: lightning (>=2.1.0)
Requires-Dist: nlp-data (>=0.2.1)
Requires-Dist: nlu-inference (>=0.3.0)
Requires-Dist: onnx (>=1.14.0)
Requires-Dist: onnxruntime (>=1.15.1)
Requires-Dist: pandas (>=1.9.0)
Requires-Dist: rich (>=13.5.3)
Requires-Dist: wasabi (>=1.1.2)
